ctu_bosh_sr450-0.1.0.dist-info/METADATA
ctu_bosh_sr450-0.1.0.dist-info/WHEEL
ctu_bosh_sr450-0.1.0.dist-info/licenses/LICENSE
ctu_bosh_sr450/__init__.py
ctu_bosh_sr450/circle_circle_intersection.py
ctu_bosh_sr450/robot_bosh.py
ctu_bosh_sr450-0.1.0.dist-info/RECORD
