Metadata-Version: 2.1
Name: ctu_bosh_sr450
Version: 0.1.0
Summary: Package to control CTU/CIIRC robot Bosh SR450 via MARS control unit.
Author-Email: Vladimir Petrik <vladimir.petrik@cvut.cz>
License: BSD 3-Clause
Requires-Python: >=3.8
Requires-Dist: numpy>=1.24.4
Requires-Dist: pyserial>=3.5
Requires-Dist: ctu-mars-control-unit>=0.1.1
